OroAutoGrammar_Ebisa/OroAutoGrammar.ipynb
OroAutoGrammar_Ebisa/__init__.py
oroautogrammar_ebisa-0.0.1.dist-info/METADATA
oroautogrammar_ebisa-0.0.1.dist-info/WHEEL
oroautogrammar_ebisa-0.0.1.dist-info/RECORD
