Metadata-Version: 2.1
Name: OroAutoGrammar-Ebisa
Version: 0.0.1
Summary: A python package that recieves an Oromo text file from a user, and generates a grammar-based dataset of Oromo phrases 
Project-URL: Homepage, https://github.com/pypa/sampleproject
Project-URL: Bug Tracker, https://github.com/pypa/sampleproject/issues
Project-URL: Github Link, https://www.github/EbisaAsfaw/OroAutoGrammar
Project-URL: Sample Text, https://www.github/EbisaAsfaw/OroAutoGrammar/oro_text.txt
Author-email: "Ebisa A. Gemechu" <lammiyad@yahoo.com>
Classifier: License :: OSI Approved :: MIT License
Classifier: Operating System :: OS Independent
Classifier: Programming Language :: Python :: 3
Requires-Python: >=3.8
